SPI_Master_Project/rtl/spi_master.v
`timescale 1ns/1ps
    module spi_master (
    input  wire       clk,
    input  wire       reset,
    input  wire       start,
    input  wire [7:0] data_in,

    output reg        busy,
    output reg        done,
    output reg        sclk,
    output reg        mosi,
    output reg        cs
);

reg [7:0] shift_reg;
reg [3:0] bit_count;

always @(posedge clk or posedge reset) begin

    if (reset) begin
        busy      <= 1'b0;
        done      <= 1'b0;
        sclk      <= 1'b0;
        mosi      <= 1'b0;
        cs        <= 1'b1;
        shift_reg <= 8'b0;
        bit_count <= 4'b0;
    end

    else begin

        done <= 1'b0;

        if (start && !busy) begin

            busy      <= 1'b1;
            cs        <= 1'b0;
            shift_reg <= data_in;
            bit_count <= 4'd0;
            mosi      <= data_in[7];
            sclk      <= 1'b0;

        end

        else if (busy) begin

            sclk <= ~sclk;

            if (sclk == 1'b1) begin

                shift_reg <= {shift_reg[6:0], 1'b0};
                bit_count <= bit_count + 1'b1;

                if (bit_count == 4'd7) begin
                    busy <= 1'b0;
                    done <= 1'b1;
                    cs   <= 1'b1;
                    mosi <= 1'b0;
                    sclk <= 1'b0;
                end

                else begin
                    mosi <= shift_reg[6];
                end

            end

        end

    end

end

endmodule

SPI_Master_Project/tb/tb_spi_master.v
`timescale 1ns/1ps

module tb_spi_master;

reg clk;
reg reset;
reg start;
reg [7:0] data_in;

wire busy;
wire done;
wire sclk;
wire mosi;
wire cs;

spi_master uut (
    .clk(clk),
    .reset(reset),
    .start(start),
    .data_in(data_in),

    .busy(busy),
    .done(done),
    .sclk(sclk),
    .mosi(mosi),
    .cs(cs)
);

always #5 clk = ~clk;

initial begin

    $dumpfile("spi_master.vcd");
    $dumpvars(0, tb_spi_master);

    clk   = 0;
    reset = 1;
    start = 0;
    data_in = 8'b00000000;

    #20;

    reset = 0;

    #20;

    data_in = 8'b10101010;
    start = 1;

    #10;

    start = 0;

    wait(done);

    #20;

    $finish;

end

endmodule

SPI_Master_Project/spi_master.vcd
$version Generated by VerilatedVcd $end
$timescale 1ps $end
 $scope module $rootio $end
 $upscope $end
 $scope module tb_spi_master $end
  $var wire 1 * clk $end
  $var wire 1 + reset $end
  $var wire 1 , start $end
  $var wire 8 - data_in [7:0] $end
  $var wire 1 # busy $end
  $var wire 1 $ done $end
  $var wire 1 % sclk $end
  $var wire 1 & mosi $end
  $var wire 1 ' cs $end
  $scope module uut $end
   $var wire 1 * clk $end
   $var wire 1 + reset $end
   $var wire 1 , start $end
   $var wire 8 - data_in [7:0] $end
   $var wire 1 # busy $end
   $var wire 1 $ done $end
   $var wire 1 % sclk $end
   $var wire 1 & mosi $end
   $var wire 1 ' cs $end
   $var wire 8 ( shift_reg [7:0] $end
   $var wire 4 ) bit_count [3:0] $end
  $upscope $end
 $upscope $end
$enddefinitions $end


#0
0#
0$
0%
0&
0'
b00000000 (
b0000 )
0*
1+
0,
b00000000 -
#5000
1'
1*
#10000
0*
#15000
1*
#20000
0*
0+
#25000
1*
#30000
0*
#35000
1*
#40000
0*
1,
b10101010 -
#45000
1#
1&
0'
b10101010 (
1*
#50000
0*
0,
#55000
1%
1*
#60000
0*
#65000
0%
0&
b01010100 (
b0001 )
1*
#70000
0*
#75000
1%
1*
#80000
0*
#85000
0%
1&
b10101000 (
b0010 )
1*
#90000
0*
#95000
1%
1*
#100000
0*
#105000
0%
0&
b01010000 (
b0011 )
1*
#110000
0*
#115000
1%
1*
#120000
0*
#125000
0%
1&
b10100000 (
b0100 )
1*
#130000
0*
#135000
1%
1*
#140000
0*
#145000
0%
0&
b01000000 (
b0101 )
1*
#150000
0*
#155000
1%
1*
#160000
0*
#165000
0%
1&
b10000000 (
b0110 )
1*
#170000
0*
#175000
1%
1*
#180000
0*
#185000
0%
0&
b00000000 (
b0111 )
1*
#190000
0*
#195000
1%
1*
#200000
0*
#205000
0#
1$
0%
1'
b1000 )
1*
#210000
0*
#215000
0$
1*
